efficiency_pipeline/__init__.py
efficiency_pipeline/lco_fakeSNpipeline.py
efficiency_pipeline/lco_figures.py
efficiency_pipeline/test_efficiency_pipeline.py
efficiency_pipeline-0.0.1.dist-info/METADATA
efficiency_pipeline-0.0.1.dist-info/WHEEL
efficiency_pipeline-0.0.1.dist-info/top_level.txt
efficiency_pipeline-0.0.1.dist-info/RECORD
